vips_utils/__init__.py
vips_utils/__main__.py
vips_utils/abi.py
vips_utils/address.py
vips_utils/applicators.py
vips_utils/conversions.py
vips_utils/crypto.py
vips_utils/currency.py
vips_utils/debug.py
vips_utils/decorators.py
vips_utils/encoding.py
vips_utils/exceptions.py
vips_utils/functional.py
vips_utils/hexadecimal.py
vips_utils/humanize.py
vips_utils/logging.py
vips_utils/module_loading.py
vips_utils/numeric.py
vips_utils/py.typed
vips_utils/toolz.py
vips_utils/types.py
vips_utils/units.py
vips_utils/curried/__init__.py
vips_utils/typing/__init__.py
vips_utils/typing/misc.py
vips_utils-1.6.4.dist-info/LICENSE
vips_utils-1.6.4.dist-info/METADATA
vips_utils-1.6.4.dist-info/WHEEL
vips_utils-1.6.4.dist-info/top_level.txt
vips_utils-1.6.4.dist-info/RECORD
