Metadata-Version: 2.1
Name: vips-utils
Version: 1.6.4
Summary: Common utility functions for ethereum codebases.
Home-page: https://github.com/VIPSTARCOIN-electrum/vips_utils
Author: Piper Merriam
Author-email: pipermerriam@gmail.com
License: MIT
Keywords: ethereum
Platform: UNKNOWN
Classifier: Intended Audience :: Developers
Classifier: License :: OSI Approved :: MIT License
Classifier: Natural Language :: English
Classifier: Programming Language :: Python :: 3
Classifier: Programming Language :: Python :: 3.5
Classifier: Programming Language :: Python :: 3.6
Classifier: Programming Language :: Python :: 3.7
Classifier: Programming Language :: Python :: Implementation :: PyPy
Requires-Python: >=3.5,!=3.5.2,<4
Requires-Dist: vips-hash (<1.0.0,>=0.1.0)
Requires-Dist: eth-typing (<3.0.0,>=1.0.0)
Requires-Dist: cytoolz (<1.0.0,>=0.8.2) ; implementation_name == "cpython"
Requires-Dist: toolz (<1,>0.8.2) ; implementation_name == "pypy"
Provides-Extra: deploy
Requires-Dist: bumpversion (<1.0.0,>=0.5.3) ; extra == 'deploy'
Requires-Dist: tox (<3.0.0,>=2.9.1) ; extra == 'deploy'
Requires-Dist: wheel (<1.0.0,>=0.30.0) ; extra == 'deploy'
Provides-Extra: dev
Requires-Dist: twine ; extra == 'dev'
Requires-Dist: Sphinx (<2,>=1.5.5) ; extra == 'dev'
Requires-Dist: sphinx-rtd-theme (<2,>=0.1.9) ; extra == 'dev'
Requires-Dist: black (<19,>=18.6b4) ; extra == 'dev'
Requires-Dist: flake8 (<4.0.0,>=3.7.0) ; extra == 'dev'
Requires-Dist: isort (==4.3.18) ; extra == 'dev'
Requires-Dist: mypy (==0.701) ; extra == 'dev'
Requires-Dist: pytest (<4.0.0,>=3.4.1) ; extra == 'dev'
Requires-Dist: hypothesis (<4.0.0,>=3.4.2) ; extra == 'dev'
Requires-Dist: pytest-pythonpath (<1.0,>=0.3) ; extra == 'dev'
Requires-Dist: bumpversion (<1.0.0,>=0.5.3) ; extra == 'dev'
Requires-Dist: tox (<3.0.0,>=2.9.1) ; extra == 'dev'
Requires-Dist: wheel (<1.0.0,>=0.30.0) ; extra == 'dev'
Provides-Extra: doc
Requires-Dist: Sphinx (<2,>=1.5.5) ; extra == 'doc'
Requires-Dist: sphinx-rtd-theme (<2,>=0.1.9) ; extra == 'doc'
Provides-Extra: lint
Requires-Dist: black (<19,>=18.6b4) ; extra == 'lint'
Requires-Dist: flake8 (<4.0.0,>=3.7.0) ; extra == 'lint'
Requires-Dist: isort (==4.3.18) ; extra == 'lint'
Requires-Dist: mypy (==0.701) ; extra == 'lint'
Requires-Dist: pytest (<4.0.0,>=3.4.1) ; extra == 'lint'
Provides-Extra: test
Requires-Dist: hypothesis (<4.0.0,>=3.4.2) ; extra == 'test'
Requires-Dist: pytest (<4.0.0,>=3.4.1) ; extra == 'test'
Requires-Dist: pytest-pythonpath (<1.0,>=0.3) ; extra == 'test'
